clak/__init__.py
clak/argparse_.py
clak/common.py
clak/comp/__init__.py
clak/comp/completion.py
clak/comp/config.py
clak/comp/logging.py
clak/exception.py
clak/nodes.py
clak/parser.py
clak/parser_BROKEN.py
clak/plugins.py
mrjk_clak-0.3.1.dist-info/LICENSE.txt
mrjk_clak-0.3.1.dist-info/METADATA
mrjk_clak-0.3.1.dist-info/WHEEL
mrjk_clak-0.3.1.dist-info/RECORD
