Metadata-Version: 2.3
Name: mrjk.clak
Version: 0.3.1
Summary: Command Line avec Klass
License: GPLv3
Author: mrjk
Author-email: mrjk.78@gmail.com
Requires-Python: >=3.9,<4.0
Classifier: License :: Other/Proprietary License
Classifier: Programming Language :: Python :: 3
Classifier: Programming Language :: Python :: 3.9
Classifier: Programming Language :: Python :: 3.10
Classifier: Programming Language :: Python :: 3.11
Classifier: Programming Language :: Python :: 3.12
Classifier: Programming Language :: Python :: 3.13
Requires-Dist: argcomplete (>=3.5.3,<4.0.0)
